{
    "pos_z": 871.9, 
    "list_of_players_inside": [], 
    "pos_x": 825.4, 
    "pos_y": 62.1, 
    "name": "CPNJtest1", 
    "tele_z": 864.4, 
    "region": [
        "1.1.7rg"
    ], 
    "tele_y": 62.1, 
    "length": "15 ", 
    "height": "10", 
    "shape": "room", 
    "width": "10", 
    "messages_dict": {
        "entering_core": "entering CPNJtest1's core", 
        "entering_boundary": "entering CPNJtest1", 
        "leaving_boundary": "leaving CPNJtest1", 
        "leaving_core": "leaving CPNJtest1's core"
    }, 
    "tele_x": 820.4, 
    "radius": 10, 
    "owner": "76561198084399656", 
    "warning_boundary": 6, 
    "identifier": "CPNJtest1"
}