{
    "deaths": 14, 
    "ip": "77.20.254.160", 
    "last_teleport": 0, 
    "id": "100500", 
    "steamid": "76561198040658370", 
    "authenticated": true, 
    "ping": 31, 
    "score": "5", 
    "health": 88, 
    "rot_z": 0.0, 
    "rot_y": -347.9, 
    "rot_x": -14.0, 
    "permission_levels": [
        "admin", 
        "authenticated", 
        "mod"
    ], 
    "pos_z": 922.1, 
    "pos_x": 697.7, 
    "pos_y": 62.1, 
    "remote": true, 
    "name": "ecv", 
    "level": "4", 
    "region": "1.1.7rg", 
    "players": 0, 
    "is_responsive": true, 
    "zombies": 22
}